{"version": "1", "message": "ERROR: Hidden Testcases server unreachable.", "problem_id": "ads2_m10_a1_1", "user_id": "gvnaakhilsurya", "score": {"sample": {"0": {"execution_time": 1.3648321628570557, "passed": true}, "1": {"execution_time": 0.6998872756958008, "passed": true}, "2": {"execution_time": 0.5296900272369385, "passed": false}, "3": {"execution_time": 0.17850184440612793, "passed": true}, "4": {"execution_time": 0.5546777248382568, "passed": false}, "5": {"execution_time": 0.6553158760070801, "passed": false}, "6": {"execution_time": 1.2779514789581299, "passed": false}, "7": {"execution_time": 0.4447948932647705, "passed": false}, "8": {"execution_time": 3.590601921081543, "passed": false}}}, "check_style_score": "0/1"}