{"version": "1", "message": "ERROR: Hidden Testcases server unreachable.", "problem_id": "ads2_m3_a1_1", "user_id": "gvnaakhilsurya", "score": {"sample": {"0": {"execution_time": 0.29660582542419434, "passed": true}, "1": {"execution_time": 0.23020172119140625, "passed": true}, "2": {"execution_time": 0.2782289981842041, "passed": true}, "3": {"execution_time": 0.29758787155151367, "passed": true}, "4": {"execution_time": 0.19259381294250488, "passed": true}, "5": {"execution_time": 0.2693824768066406, "passed": true}, "6": {"execution_time": 0.2374098300933838, "passed": true}, "7": {"execution_time": 0.22687244415283203, "passed": true}}}, "check_style_score": "1/1"}