{"version": "1", "message": "ERROR: Hidden Testcases server unreachable.", "problem_id": "ads2_m3_a1_1", "user_id": "gvnaakhilsurya", "score": {"sample": {"0": {"execution_time": 0.4410989284515381, "passed": true}, "1": {"execution_time": 0.1990201473236084, "passed": true}, "2": {"execution_time": 0.3060009479522705, "passed": true}, "3": {"execution_time": 0.24936580657958984, "passed": true}, "4": {"execution_time": 0.1801445484161377, "passed": true}, "5": {"execution_time": 0.24054312705993652, "passed": true}, "6": {"execution_time": 0.20014429092407227, "passed": true}, "7": {"execution_time": 0.17829656600952148, "passed": true}}}, "check_style_score": "0/1"}